Metadata-Version: 1.1
Name: cliffdemo
Version: 0.1
Summary: Demo app for cliff
Home-page: https://github.com/dreamhost/cliff
Author: Doug Hellmann
Author-email: doug.hellmann@gmail.com
License: UNKNOWN
Download-URL: https://github.com/dreamhost/cliff/tarball/master
Platform: Any
Classifier: Development Status :: 3 - Alpha
Classifier: License :: OSI Approved :: Apache Software License
Classifier: Programming Language :: Python
Classifier: Programming Language :: Python :: 2
Classifier: Programming Language :: Python :: 2.7
Classifier: Programming Language :: Python :: 3
Classifier: Programming Language :: Python :: 3.2
Classifier: Intended Audience :: Developers
Classifier: Environment :: Console
